channels_irc/__init__.py
channels_irc/cli.py
channels_irc/client.py
channels_irc/consumers.py
channels_irc/multi.py
channels_irc/server.py
channels_irc/tests/__init__.py
channels_irc/tests/settings.py
channels_irc/tests/test_client.py
channels_irc/tests/test_consumers.py
channels_irc/tests/test_multi.py
channels_irc/tests/utils.py
channels_irc-0.7.1.dist-info/LICENSE.txt
channels_irc-0.7.1.dist-info/METADATA
channels_irc-0.7.1.dist-info/WHEEL
channels_irc-0.7.1.dist-info/entry_points.txt
channels_irc-0.7.1.dist-info/top_level.txt
channels_irc-0.7.1.dist-info/RECORD
