Metadata-Version: 2.1
Name: channels-irc
Version: 0.7.1
Summary: Interface server connecting Django's channels and IRC
Home-page: https://github.com/AdvocatesInc/django-channels-irc
Author: Advocates, Inc
Author-email: admin@adv.gg
License: Proprietary and confidential
Classifier: Environment :: Web Environment
Classifier: Framework :: Django
Classifier: Intended Audience :: Developers
Classifier: License :: OSI Approved :: MIT License
Classifier: Operating System :: OS Independent
Classifier: Programming Language :: Python
Classifier: Programming Language :: Python :: 3
Classifier: Programming Language :: Python :: 3.5
Classifier: Programming Language :: Python :: 3.6
Classifier: Programming Language :: Python :: 3.7
Classifier: Topic :: Internet :: WWW/HTTP
License-File: LICENSE.txt
Requires-Dist: irc (>=16.4)
Requires-Dist: channels (>=3.0.0)
Requires-Dist: asgiref (>=3.0.0)
